LICENSE
MANIFEST.in
README.md
requirements.txt
setup.py
oms_gallery/__init__.py
oms_gallery/admin.py
oms_gallery/apps.py
oms_gallery/forms.py
oms_gallery/models.py
oms_gallery/tests.py
oms_gallery/views.py
oms_gallery/migrations/0001_initial.py
oms_gallery/migrations/0002_auto_20190714_1348.py
oms_gallery/migrations/0003_auto_20200229_1105.py
oms_gallery/migrations/__init__.py
oms_gallery/templates/oms_gallery/admin/change_list.html
oms_gallery/templates/oms_gallery/admin/upload_zip.html
oms_gallery/templatetags/__init__.py
oms_gallery/templatetags/gallery_tags.py