Metadata-Version: 1.1
Name: oms_gallery
Version: 0.4.2
Summary: Image management for Django.
Home-page: https://github.com/DJWOMS/oms-gallery
Author: Omelchenko Michael - DJWOMS
Author-email: djwoms@gmail.com
License: UNKNOWN
Platform: UNKNOWN
Classifier: Development Status :: 4 - Beta
Classifier: Environment :: Web Environment
Classifier: Framework :: Django
Classifier: Intended Audience :: Developers
Classifier: License :: OSI Approved :: BSD License
Classifier: Operating System :: OS Independent
Classifier: Programming Language :: Python
Classifier: Programming Language :: Python :: 3
Classifier: Programming Language :: Python :: 3.7
Classifier: Programming Language :: Python :: 3.8
Classifier: Topic :: Utilities
